maildirwatch.py
maildirwatch-0.2.1.dist-info/licenses/LICENSE
maildirwatch-0.2.1.dist-info/METADATA
maildirwatch-0.2.1.dist-info/WHEEL
maildirwatch-0.2.1.dist-info/entry_points.txt
maildirwatch-0.2.1.dist-info/top_level.txt
maildirwatch-0.2.1.dist-info/RECORD
