Metadata-Version: 2.4
Name: maildirwatch
Version: 0.2.1
Summary: Watch Maildir for incoming mail and display notifications
Home-page: https://github.com/mkcms/maildirwatch
Download-URL: https://github.com/mkcms/maildirwatch/archive/v0.2.1.tar.gz
Author: Michał Krzywkowski
Author-email: k.michal@zoho.com
License: GPLv3
Classifier: Development Status :: 3 - Alpha
Classifier: Intended Audience :: End Users/Desktop
Classifier: License :: OSI Approved :: GNU General Public License v3 or later (GPLv3+)
Classifier: Programming Language :: Python :: 3 :: Only
Classifier: Programming Language :: Python :: 3
Classifier: Topic :: Communications :: Email
Classifier: Topic :: Internet
License-File: LICENSE
Requires-Dist: PyGObject==3.50.0
Dynamic: author
Dynamic: author-email
Dynamic: classifier
Dynamic: description
Dynamic: download-url
Dynamic: home-page
Dynamic: license
Dynamic: license-file
Dynamic: requires-dist
Dynamic: summary
